weelib/__init__.py
weelib/validator.py
weelib-0.1.7.dist-info/METADATA
weelib-0.1.7.dist-info/WHEEL
weelib-0.1.7.dist-info/top_level.txt
weelib-0.1.7.dist-info/RECORD
