Metadata-Version: 2.1
Name: weelib
Version: 0.1.7
Summary: Additional functions for weepy framework.
Home-page: https://gitlab.com/katry/weelib
Author: Patrik Katrenak
Author-email: patrik@katryapps.com
Platform: any
Classifier: Programming Language :: Python :: 3
Classifier: License :: OSI Approved :: GNU General Public License v3 or later (GPLv3+)
Classifier: Operating System :: OS Independent
Classifier: Development Status :: 3 - Alpha
Classifier: Intended Audience :: Developers
Classifier: Topic :: Software Development :: Libraries
Classifier: Natural Language :: English
Requires-Python: >=3.10
